MANIFEST.in
galerts.py
setup.py
docs/.CHANGES.rst.swp
docs/CHANGES.rst
docs/COPYING.txt
docs/Makefile
docs/README.rst
docs/conf.py
docs/galerts.rst
docs/index.rst
docs/build/doctrees/CHANGES.doctree
docs/build/doctrees/README.doctree
docs/build/doctrees/environment.pickle
docs/build/doctrees/galerts.doctree
docs/build/doctrees/index.doctree
docs/build/html/.buildinfo
docs/build/html/CHANGES.html
docs/build/html/README.html
docs/build/html/galerts.html
docs/build/html/genindex.html
docs/build/html/index.html
docs/build/html/modindex.html
docs/build/html/objects.inv
docs/build/html/search.html
docs/build/html/searchindex.js
docs/build/html/_sources/CHANGES.txt
docs/build/html/_sources/README.txt
docs/build/html/_sources/galerts.txt
docs/build/html/_sources/index.txt
docs/build/html/_static/basic.css
docs/build/html/_static/default.css
docs/build/html/_static/doctools.js
docs/build/html/_static/file.png
docs/build/html/_static/jquery.js
docs/build/html/_static/minus.png
docs/build/html/_static/plus.png
docs/build/html/_static/pygments.css
docs/build/html/_static/searchtools.js
galerts.egg-info/PKG-INFO
galerts.egg-info/SOURCES.txt
galerts.egg-info/dependency_links.txt
galerts.egg-info/requires.txt
galerts.egg-info/top_level.txt
galerts.egg-info/zip-safe