Metadata-Version: 1.0
Name: galerts
Version: 0.1.5
Summary: Python libary for managing Google Alerts
Home-page: http://jab.github.com/galerts/
Author: Josh Bronson
Author-email: jabronson@gmail.com
License: MIT
Keywords: google,alerts,google alerts,news
Platform: UNKNOWN
Classifier: Development Status :: 3 - Alpha
Classifier: License :: OSI Approved :: MIT License
Classifier: Topic :: Internet :: WWW/HTTP :: Dynamic Content :: News/Diary
Classifier: Topic :: Internet :: WWW/HTTP :: Indexing/Search
